devart/netsuite/__init__.py
devart/netsuite/netsuite.cp37-win32.pyd
devart/netsuite/netsuite.pyi
devart/netsuite/NetSuite/Devart.Python.NetSuiteEngine.dll
devart/netsuite/NetSuite/sqlite3.dll
devart/netsuite/sqlalchemy/__init__.py
devart_netsuite_connector-1.2.0.dist-info/LICENSE
devart_netsuite_connector-1.2.0.dist-info/METADATA
devart_netsuite_connector-1.2.0.dist-info/WHEEL
devart_netsuite_connector-1.2.0.dist-info/top_level.txt
devart_netsuite_connector-1.2.0.dist-info/RECORD
